fscan/__init__.py
fscan/__main__.py
fscan/_version.py
fscan/batch.py
fscan/clean.py
fscan/html.py
fscan/post.py
fscan/status.py
fscan/plot/__init__.py
fscan/plot/finetoothplot.py
fscan/plot/linecount.py
fscan/plot/static.py
fscan/process/__init__.py
fscan/process/autotag.py
fscan/process/combfinder.py
fscan/process/history.py
fscan/process/linefinder.py
fscan/process/lineobjects.py
fscan/process/spectlinetools.py
fscan/utils/__init__.py
fscan/utils/config.py
fscan/utils/dtutils.py
fscan/utils/io.py
fscan/utils/reuse.py
fscan/utils/segments.py
fscan/utils/utils.py
fscan-0.6.4.dist-info/licenses/LICENSE
fscan-0.6.4.dist-info/METADATA
fscan-0.6.4.dist-info/WHEEL
fscan-0.6.4.dist-info/entry_points.txt
fscan-0.6.4.dist-info/top_level.txt
fscan-0.6.4.dist-info/RECORD
