Metadata-Version: 2.4
Name: fscan
Version: 0.6.4
Summary: Fscan tool for monitoring narrow spectral artifacts in LIGO data
Author-email: Evan Goetz <evan.goetz@ligo.org>, Ansel Neunzert <ansel.neunzert@ligo.org>, Sudhagar Suyamprakasam <sudhagar.suyamprakasam@ligo.org>
License-Expression: GPL-3.0-or-later
Project-URL: Source Code, https://git.ligo.org/CW/instrumental/fscan
Project-URL: Bug Tracker, https://git.ligo.org/CW/instrumental/fscan/-/issues
Classifier: Development Status :: 5 - Production/Stable
Classifier: Intended Audience :: Science/Research
Classifier: Natural Language :: English
Classifier: Operating System :: OS Independent
Classifier: Programming Language :: Python
Classifier: Programming Language :: Python :: 3
Classifier: Programming Language :: Python :: 3.10
Classifier: Programming Language :: Python :: 3.11
Classifier: Topic :: Scientific/Engineering :: Astronomy
Classifier: Topic :: Scientific/Engineering :: Physics
Requires-Python: >=3.10
License-File: LICENSE
Requires-Dist: bokeh>=3.7.2
Requires-Dist: gwdetchar
Requires-Dist: gpstime
Provides-Extra: test
Requires-Dist: flake8; extra == "test"
Provides-Extra: conda
Requires-Dist: lalpulsar>=7.1.1; extra == "conda"
Requires-Dist: lalframe; extra == "conda"
Provides-Extra: docs
Requires-Dist: sphinx<9.0.0; extra == "docs"
Requires-Dist: sphinx-immaterial-igwn; extra == "docs"
Requires-Dist: numpydoc; extra == "docs"
Dynamic: license-file
